Metadata-Version: 1.1
Name: drf-api-dump
Version: 0.1.3
Summary: Dumps data from apps or models via HTTP
Home-page: https://github.com/davidvicenteranz/drf-api-dump/
Author: David Vicente Ranz
Author-email: dvicente74@gmail.com
License: MIT license
Keywords: django dumpdata development
Platform: UNKNOWN
Classifier: Framework :: Django
Classifier: Development Status :: 4 - Beta
Classifier: Environment :: Web Environment
Classifier: Intended Audience :: Developers
Classifier: License :: OSI Approved :: MIT License
Classifier: Programming Language :: Python
Classifier: Programming Language :: Python :: 2
Classifier: Programming Language :: Python :: 2.6
Classifier: Programming Language :: Python :: 2.7
Classifier: Topic :: Software Development :: Libraries :: Python Modules
